<?xml version="1.0"?>
<checkstyle><file name="modules/contrib/braintree_api/src/Event/BraintreeApiWebhookEvent.php"><error line="11" message="Class Drupal\braintree_api\Event\BraintreeApiWebhookEvent extends deprecated class Symfony\Component\EventDispatcher\Event: since Symfony 4.3, use &quot;Symfony\Contracts\EventDispatcher\Event&quot; instead" severity="error"/></file><file name="modules/contrib/braintree_api/braintree_api.info.yml"><error line="0" message="Value of core_version_requirement: ^8 || ^9 is not compatible with the next major version of Drupal core. See https://drupal.org/node/3070687." severity="error"/></file><file name="modules/contrib/braintree_api/modules/braintree_api_test/braintree_api_test.info.yml"><error line="0" message="Value of core_version_requirement: ^8 || ^9 is not compatible with the next major version of Drupal core. See https://drupal.org/node/3070687." severity="error"/></file></checkstyle>

