<?xml version="1.0"?>
<checkstyle><file name="modules/contrib/minifier_html/src/EventSubscriber/MinifierHtmlSubscriber.php"><error line="38" message="Parameter $event of method Drupal\minifier_html\EventSubscriber\MinifierHtmlSubscriber::minifilterHtmlResponse() has typehint with deprecated class Symfony\Component\HttpKernel\Event\FilterResponseEvent: since Symfony 4.3, use ResponseEvent instead" severity="error"/></file><file name="modules/contrib/minifier_html/tests/src/Functional/LoadTest.php"><error line="43" message="Call to deprecated method assertResponse() of class Drupal\Tests\BrowserTestBase. Deprecated in drupal:8.2.0 and is removed from drupal:10.0.0. Use $this-&gt;assertSession()-&gt;statusCodeEquals() instead." severity="error"/></file><file name="modules/contrib/minifier_html/minifier_html.info.yml"><error line="0" message="Value of core_version_requirement: ^8 || ^9 is not compatible with the next major version of Drupal core. See https://drupal.org/node/3070687." severity="error"/></file></checkstyle>

