<?xml version="1.0"?>
<checkstyle><file name="modules/contrib/cattask_alpha_theme_support/src/Plugin/Block/BannerBrushBubble.php"><error line="109" message="Call to deprecated function file_create_url(). Deprecated in drupal:9.3.0 and is removed from drupal:10.0.0. Use the appropriate method on \Drupal\Core\File\FileUrlGeneratorInterface instead." severity="warning"/></file><file name="modules/contrib/cattask_alpha_theme_support/tests/src/Functional/LoadTest.php"><error line="13" message="Drupal\Tests\BrowserTestBase::$defaultTheme is required. See https://www.drupal.org/node/3083055, which includes recommendations on which theme to use." severity="error"/></file><file name="modules/contrib/cattask_alpha_theme_support/cattask_alpha_theme_support.info.yml"><error line="0" message="Value of core_version_requirement: ^8.8 || ^9 is not compatible with the next major version of Drupal core. See https://drupal.org/node/3070687." severity="error"/></file></checkstyle>

