<?xml version="1.0"?>
<checkstyle><file name="modules/contrib/sagepay/src/Form/CreditCardTerminalFormAlter.php"><error line="" message="Class Drupal\uc_credit\Form\CreditCardTerminalForm not found." severity="error"/><error line="13" message="Class Drupal\uc_credit\Form\CreditCardTerminalForm not found." severity="error"/></file><file name="modules/contrib/sagepay/src/Plugin/Ubercart/PaymentMethod/SagePay.php"><error line="" message="Class Drupal\uc_credit\CreditCardPaymentMethodBase not found." severity="error"/><error line="23" message="Class Drupal\uc_credit\CreditCardPaymentMethodBase not found." severity="error"/></file><file name="modules/contrib/sagepay"><error line="0" message="The 'uc_sagepay' extension is not installed. Cannot check deprecated library use." severity="error"/></file><file name="modules/contrib/sagepay/uc_sagepay.info.yml"><error line="0" message="Value of core_version_requirement: ^8.8 || ^9 is not compatible with the next major version of Drupal core. See https://drupal.org/node/3070687." severity="error"/></file></checkstyle>

